pmec_url_checker/__init__.py
pmec_url_checker/dns_resolver.py
pmec_url_checker/main.py
pmec_url_checker/url_checker.py
pmec_url_checker/url_db.py
pmec_url_checker-0.0.2.dist-info/METADATA
pmec_url_checker-0.0.2.dist-info/WHEEL
pmec_url_checker-0.0.2.dist-info/entry_points.txt
pmec_url_checker-0.0.2.dist-info/top_level.txt
pmec_url_checker-0.0.2.dist-info/RECORD
