Metadata-Version: 2.1
Name: pmec-url-checker
Version: 0.0.2
Summary: URL checker tool for AP5GC.
Home-page: UNKNOWN
Author: Sagar Bhatt
Author-email: sagbhatt@microsoft.com
License: Copyright (c) Microsoft Corporation. All rights reserved.
Platform: any
Requires-Python: >=3.9
Requires-Dist: requests >=2.31.0
Requires-Dist: dnspython >=2.6.1
Requires-Dist: pandas >=2.2.1
